redbase/__init__.py
redbase/_version.py
redbase/base.py
redbase/operation.py
redbase/ext/__init__.py
redbase/ext/memory.py
redbase/ext/mongo.py
redbase/ext/sqlalchemy.py
redbase/tests/__init__.py
redbase/tests/conftest.py
redbase/tests/test_common.py
redbase/tests/test_memory.py
redbase/tests/test_sqlalchemy.py
redbase-0.0.0.dist-info/METADATA
redbase-0.0.0.dist-info/WHEEL
redbase-0.0.0.dist-info/top_level.txt
redbase-0.0.0.dist-info/RECORD
