Metadata-Version: 2.1
Name: redbase
Version: 0.0.0
Summary: Repository Patterns for Python
Home-page: https://github.com/Miksus/red-base.git
Author: Mikael Koli
Author-email: koli.mikael@gmail.com
License: UNKNOWN
Platform: UNKNOWN
Classifier: Operating System :: OS Independent
Classifier: License :: OSI Approved :: MIT License
Classifier: Programming Language :: Python :: 3
Classifier: Programming Language :: Python :: 3.8
Classifier: Intended Audience :: Developers
Requires-Python: >=3.6.0
